sdm_modbus_zmq/__init__.py
sdm_modbus_zmq/app.py
sdm_modbus_zmq/client.py
sdm_modbus_zmq/const.py
sdm_modbus_zmq/server.py
sdm_modbus_zmq-0.0.1.dist-info/LICENSE
sdm_modbus_zmq-0.0.1.dist-info/METADATA
sdm_modbus_zmq-0.0.1.dist-info/WHEEL
sdm_modbus_zmq-0.0.1.dist-info/entry_points.txt
sdm_modbus_zmq-0.0.1.dist-info/top_level.txt
sdm_modbus_zmq-0.0.1.dist-info/RECORD
