Metadata-Version: 2.1
Name: sdm-modbus-zmq
Version: 0.0.1
Summary: SDM Modbus ZeroMQ client and server
Home-page: https://github.com/bertybuttface/sdm-modbus-zmq
Project-URL: Bug Tracker, https://github.com/bertybuttface/sdm-modbus-zmq/issues
Project-URL: Changelog, https://github.com/bertybuttface/sdm-modbus-zmq/releases
Classifier: Programming Language :: Python :: 3
Classifier: License :: OSI Approved :: BSD License
Classifier: Intended Audience :: Developers
Requires-Python: >=3.6
License-File: LICENSE
Requires-Dist: pyzmq (>=24.0.1)
